ssh_file_server/__init__.py
ssh_file_server/server.py
ssh_file_server-0.1.2.dist-info/METADATA
ssh_file_server-0.1.2.dist-info/RECORD
ssh_file_server-0.1.2.dist-info/WHEEL
ssh_file_server-0.1.2.dist-info/top_level.txt
